tap_csv_folder/__init__.py
tap_csv_folder/__main__.py
tap_csv_folder/client.py
tap_csv_folder/tap.py
tap_csv_folder-0.0.1a1.dist-info/LICENSE
tap_csv_folder-0.0.1a1.dist-info/METADATA
tap_csv_folder-0.0.1a1.dist-info/WHEEL
tap_csv_folder-0.0.1a1.dist-info/entry_points.txt
tap_csv_folder-0.0.1a1.dist-info/RECORD
