Metadata-Version: 2.1
Name: tap-csv-folder
Version: 0.0.1a1
Summary: Singer tap for CSVFolder, built with the Meltano Singer SDK.
License: Apache-2.0
Keywords: ELT,CSVFolder
Author: Edgar Ramírez-Mondragón
Author-email: edgar@arch.dev
Requires-Python: >=3.9
Classifier: Intended Audience :: Developers
Classifier: License :: OSI Approved :: Apache Software License
Classifier: Operating System :: OS Independent
Classifier: Programming Language :: Python :: 3
Classifier: Programming Language :: Python :: 3.9
Classifier: Programming Language :: Python :: 3.10
Classifier: Programming Language :: Python :: 3.11
Classifier: Programming Language :: Python :: 3.12
Classifier: Programming Language :: Python :: 3.13
Provides-Extra: testing
Requires-Dist: pytest (>=8) ; extra == "testing"
Requires-Dist: singer-sdk[s3,ssh] (>=0.41.0,<0.42.0)
